preprocessRawText/__init__.py
preprocessRawText/pretreatment.py
preprocessRawText/vietnamese-stopwords-dash.txt
preprocessRawText-0.0.28.dist-info/LICENSE
preprocessRawText-0.0.28.dist-info/METADATA
preprocessRawText-0.0.28.dist-info/WHEEL
preprocessRawText-0.0.28.dist-info/top_level.txt
preprocessRawText-0.0.28.dist-info/RECORD
