Metadata-Version: 2.1
Name: preprocessRawText
Version: 0.0.28
Summary: preprocessRawText NLP
Home-page: https://github.com/nguyenthohy/preprocess.git
Author: nguyentho
Author-email: nguyentho0207@gmail.com
License: UNKNOWN
Platform: UNKNOWN
Classifier: Programming Language :: Python :: 3
Classifier: Programming Language :: Python :: 3.5
Classifier: Programming Language :: Python :: 3.6
Classifier: Operating System :: OS Independent
Classifier: Intended Audience :: Developers
Classifier: License :: OSI Approved :: MIT License
Requires-Dist: gensim
Requires-Dist: pyvi
